[
  {
    "question": "The Slave Trade Act of 1807 abolished the British slave trade but",
    "options": [
      "Hunters on Hispaniola who smoked meat on a boucan before becoming pirates",
      "Did not free enslaved people already held in the colonies",
      "The national hero of Guyana",
      "The western Caribbean, used partly as a privateering base"
    ],
    "correctIndex": 1
  },
  {
    "question": "The Providence Island Colony was an early English Caribbean settlement in",
    "options": [
      "The western Caribbean, used partly as a privateering base",
      "Near-total dependence on food imports, a vulnerability that persists today",
      "Hunters on Hispaniola who smoked meat on a boucan before becoming pirates",
      "Tortuga (off the coast of Hispaniola)"
    ],
    "correctIndex": 0
  },
  {
    "question": "The Berbice Rebellion leader Cuffy is now",
    "options": [
      "Hunters on Hispaniola who smoked meat on a boucan before becoming pirates",
      "Overseas departments of France",
      "The national hero of Guyana",
      "Significant social reforms including education, housing and labour rights"
    ],
    "correctIndex": 2
  },
  {
    "question": "The French Caribbean islands of Martinique and Guadeloupe today have status as",
    "options": [
      "The 1938 Moyne Commission investigation into Caribbean labour conditions",
      "Hunters on Hispaniola who smoked meat on a boucan before becoming pirates",
      "Overseas departments of France",
      "The western Caribbean, used partly as a privateering base"
    ],
    "correctIndex": 2
  },
  {
    "question": "The 'free village' movement in post-emancipation Jamaica was led by",
    "options": [
      "Hunters on Hispaniola who smoked meat on a boucan before becoming pirates",
      "The western Caribbean, used partly as a privateering base",
      "The second independent nation in the Western Hemisphere",
      "Baptist missionaries, notably William Knibb"
    ],
    "correctIndex": 3
  },
  {
    "question": "The Spanish mission system used in the Greater Antilles primarily served to",
    "options": [
      "The western Caribbean, used partly as a privateering base",
      "Baptist missionaries, notably William Knibb",
      "Near-total dependence on food imports, a vulnerability that persists today",
      "Convert Indigenous people and extract their labour"
    ],
    "correctIndex": 3
  },
  {
    "question": "The term 'Buccaneer' originally referred to",
    "options": [
      "Hunters on Hispaniola who smoked meat on a boucan before becoming pirates",
      "Overseas departments of France",
      "1925",
      "Did not free enslaved people already held in the colonies"
    ],
    "correctIndex": 0
  },
  {
    "question": "The Elective Principle was introduced to Trinidad's legislature in",
    "options": [
      "Did not free enslaved people already held in the colonies",
      "Hunters on Hispaniola who smoked meat on a boucan before becoming pirates",
      "1925",
      "Near-total dependence on food imports, a vulnerability that persists today"
    ],
    "correctIndex": 2
  },
  {
    "question": "The Haitian Revolution produced the world's first Black republic and",
    "options": [
      "Hunters on Hispaniola who smoked meat on a boucan before becoming pirates",
      "The second independent nation in the Western Hemisphere",
      "Overseas departments of France",
      "Enslaved people who cultivated provision grounds as a form of resistance and economic survival"
    ],
    "correctIndex": 1
  },
  {
    "question": "The Butler Riots of 1937 in Trinidad directly influenced",
    "options": [
      "Hunters on Hispaniola who smoked meat on a boucan before becoming pirates",
      "The 1938 Moyne Commission investigation into Caribbean labour conditions",
      "Enslaved people who cultivated provision grounds as a form of resistance and economic survival",
      "Overseas departments of France"
    ],
    "correctIndex": 1
  },
  {
    "question": "The Royal Commission (Moyne Commission) recommended",
    "options": [
      "Did not free enslaved people already held in the colonies",
      "Baptist missionaries, notably William Knibb",
      "Convert Indigenous people and extract their labour",
      "Significant social reforms including education, housing and labour rights"
    ],
    "correctIndex": 3
  },
  {
    "question": "The concept of 'proto-peasantry' in Caribbean history describes",
    "options": [
      "The national hero of Guyana",
      "Enslaved people who cultivated provision grounds as a form of resistance and economic survival",
      "Did not free enslaved people already held in the colonies",
      "Tortuga (off the coast of Hispaniola)"
    ],
    "correctIndex": 1
  },
  {
    "question": "The Buccaneers of the Caribbean operated mainly out of",
    "options": [
      "Tortuga (off the coast of Hispaniola)",
      "The 1938 Moyne Commission investigation into Caribbean labour conditions",
      "Baptist missionaries, notably William Knibb",
      "Hunters on Hispaniola who smoked meat on a boucan before becoming pirates"
    ],
    "correctIndex": 0
  },
  {
    "question": "The economic doctrine that shaped European colonisation of the Caribbean was",
    "options": [
      "Mercantilism — colonies existed to enrich the mother country",
      "The western Caribbean, used partly as a privateering base",
      "Tortuga (off the coast of Hispaniola)",
      "Did not free enslaved people already held in the colonies"
    ],
    "correctIndex": 0
  },
  {
    "question": "The Caribbean's sugar monoculture led to",
    "options": [
      "Near-total dependence on food imports, a vulnerability that persists today",
      "Enslaved people who cultivated provision grounds as a form of resistance and economic survival",
      "The western Caribbean, used partly as a privateering base",
      "Baptist missionaries, notably William Knibb"
    ],
    "correctIndex": 0
  }
]