[
  {
    "question": "The concept of 'the Anthropocene' in geography",
    "options": [
      "Compact development, transit-oriented design and mixed land use",
      "Financial incentives for landowners to conserve natural ecosystems",
      "Settlement patterns exist on a spectrum rather than in distinct categories",
      "The current geological epoch defined by dominant human impact on Earth systems"
    ],
    "correctIndex": 3
  },
  {
    "question": "'Planetary boundaries' framework identifies",
    "options": [
      "The capacity of a system to absorb disturbance and reorganise while undergoing change",
      "Compact development, transit-oriented design and mixed land use",
      "Settlement patterns exist on a spectrum rather than in distinct categories",
      "Nine Earth system processes within which humanity can safely operate"
    ],
    "correctIndex": 3
  },
  {
    "question": "The concept of 'socio-ecological systems'",
    "options": [
      "Cities consume inputs and produce outputs of energy, water, food and waste",
      "Settlement patterns exist on a spectrum rather than in distinct categories",
      "Financial incentives for landowners to conserve natural ecosystems",
      "Human and natural systems are deeply interconnected and co-evolving"
    ],
    "correctIndex": 3
  },
  {
    "question": "'Resilience theory' in geography",
    "options": [
      "Cities consume inputs and produce outputs of energy, water, food and waste",
      "Settlement patterns exist on a spectrum rather than in distinct categories",
      "The capacity of a system to absorb disturbance and reorganise while undergoing change",
      "Rapid unplanned growth, poor infrastructure and environmental degradation"
    ],
    "correctIndex": 2
  },
  {
    "question": "The concept of 'urban metabolism'",
    "options": [
      "Seasonal droughts, contamination, saltwater intrusion and aging infrastructure",
      "Financial incentives for landowners to conserve natural ecosystems",
      "Cities consume inputs and produce outputs of energy, water, food and waste",
      "Compact development, transit-oriented design and mixed land use"
    ],
    "correctIndex": 2
  },
  {
    "question": "'Peri-urban areas' face challenges of",
    "options": [
      "Benefits humans receive from natural systems including clean air, water and pollination",
      "Vulnerability to multiple natural and human hazards simultaneously",
      "Rapid unplanned growth, poor infrastructure and environmental degradation",
      "Nine Earth system processes within which humanity can safely operate"
    ],
    "correctIndex": 2
  },
  {
    "question": "The concept of 'the urban-rural continuum'",
    "options": [
      "Settlement patterns exist on a spectrum rather than in distinct categories",
      "The current geological epoch defined by dominant human impact on Earth systems",
      "Benefits humans receive from natural systems including clean air, water and pollination",
      "Rapid unplanned growth, poor infrastructure and environmental degradation"
    ],
    "correctIndex": 0
  },
  {
    "question": "'Smart growth' urban policy promotes",
    "options": [
      "The capacity of a system to absorb disturbance and reorganise while undergoing change",
      "The current geological epoch defined by dominant human impact on Earth systems",
      "Human and natural systems are deeply interconnected and co-evolving",
      "Compact development, transit-oriented design and mixed land use"
    ],
    "correctIndex": 3
  },
  {
    "question": "The concept of 'just transition'",
    "options": [
      "Ensuring the shift to a green economy is fair and supports affected workers",
      "Rapid unplanned growth, poor infrastructure and environmental degradation",
      "The current geological epoch defined by dominant human impact on Earth systems",
      "Seasonal droughts, contamination, saltwater intrusion and aging infrastructure"
    ],
    "correctIndex": 0
  },
  {
    "question": "'Water security' challenges in the Caribbean include",
    "options": [
      "Benefits humans receive from natural systems including clean air, water and pollination",
      "Rapid unplanned growth, poor infrastructure and environmental degradation",
      "Seasonal droughts, contamination, saltwater intrusion and aging infrastructure",
      "Compact development, transit-oriented design and mixed land use"
    ],
    "correctIndex": 2
  },
  {
    "question": "The concept of 'ecosystem services'",
    "options": [
      "The capacity of a system to absorb disturbance and reorganise while undergoing change",
      "Financial incentives for landowners to conserve natural ecosystems",
      "Benefits humans receive from natural systems including clean air, water and pollination",
      "Compact development, transit-oriented design and mixed land use"
    ],
    "correctIndex": 2
  },
  {
    "question": "'Payments for ecosystem services'",
    "options": [
      "Ensuring the shift to a green economy is fair and supports affected workers",
      "The capacity of a system to absorb disturbance and reorganise while undergoing change",
      "Human and natural systems are deeply interconnected and co-evolving",
      "Financial incentives for landowners to conserve natural ecosystems"
    ],
    "correctIndex": 3
  },
  {
    "question": "The concept of 'multi-hazard risk'",
    "options": [
      "The capacity of a system to absorb disturbance and reorganise while undergoing change",
      "Seasonal droughts, contamination, saltwater intrusion and aging infrastructure",
      "Benefits humans receive from natural systems including clean air, water and pollination",
      "Vulnerability to multiple natural and human hazards simultaneously"
    ],
    "correctIndex": 3
  },
  {
    "question": "'Comprehensive risk management' in the Caribbean",
    "options": [
      "Integrating disaster risk reduction into development planning",
      "The capacity of a system to absorb disturbance and reorganise while undergoing change",
      "Settlement patterns exist on a spectrum rather than in distinct categories",
      "Financial incentives for landowners to conserve natural ecosystems"
    ],
    "correctIndex": 0
  },
  {
    "question": "The concept of 'blue economy' for Caribbean SIDS",
    "options": [
      "Cities consume inputs and produce outputs of energy, water, food and waste",
      "Sustainably managing ocean resources for economic growth and food security",
      "Compact development, transit-oriented design and mixed land use",
      "Benefits humans receive from natural systems including clean air, water and pollination"
    ],
    "correctIndex": 1
  }
]