[
  {
    "question": "The word equation for respiration",
    "options": [
      "Na",
      "Glucose + oxygen → carbon dioxide + water + energy",
      "A mixture of two or more metals",
      "The bronchi and lungs"
    ],
    "answer": "Glucose + oxygen → carbon dioxide + water + energy"
  },
  {
    "question": "Voltage is measured using a",
    "options": [
      "Break down dead organic matter",
      "Voltmeter",
      "Different rates of movement through a medium",
      "Current is the same throughout in series"
    ],
    "answer": "Voltmeter"
  },
  {
    "question": "The part of the brain that controls balance and coordination",
    "options": [
      "Cerebellum",
      "Force × Distance",
      "3 × 10⁸ m/s",
      "Plant growth towards light"
    ],
    "answer": "Cerebellum"
  },
  {
    "question": "An alloy is",
    "options": [
      "A mixture of two or more metals",
      "Plant growth towards light",
      "Voltmeter",
      "Current is the same throughout in series"
    ],
    "answer": "A mixture of two or more metals"
  },
  {
    "question": "Work done is calculated as",
    "options": [
      "Using a separating funnel",
      "Cerebellum",
      "Force × Distance",
      "Voltmeter"
    ],
    "answer": "Force × Distance"
  },
  {
    "question": "The process by which organisms produce offspring",
    "options": [
      "Plant growth towards light",
      "Cerebellum",
      "Na",
      "Reproduction"
    ],
    "answer": "Reproduction"
  },
  {
    "question": "Chromatography separates mixtures based on",
    "options": [
      "Glucose + oxygen → carbon dioxide + water + energy",
      "Current is the same throughout in series",
      "Plant growth towards light",
      "Different rates of movement through a medium"
    ],
    "answer": "Different rates of movement through a medium"
  },
  {
    "question": "The function of the alveoli",
    "options": [
      "Na",
      "Force × Distance",
      "Voltmeter",
      "Gaseous exchange in the lungs"
    ],
    "answer": "Gaseous exchange in the lungs"
  },
  {
    "question": "A series circuit differs from a parallel circuit because",
    "options": [
      "Voltmeter",
      "Force × Distance",
      "Current is the same throughout in series",
      "Break down dead organic matter"
    ],
    "answer": "Current is the same throughout in series"
  },
  {
    "question": "The symbol for sodium",
    "options": [
      "Na",
      "Gaseous exchange in the lungs",
      "Cerebellum",
      "Reproduction"
    ],
    "answer": "Na"
  },
  {
    "question": "Phototropism is",
    "options": [
      "Plant growth towards light",
      "A mixture of two or more metals",
      "Cerebellum",
      "Different rates of movement through a medium"
    ],
    "answer": "Plant growth towards light"
  },
  {
    "question": "A mixture of oil and water can be separated by",
    "options": [
      "The bronchi and lungs",
      "Voltmeter",
      "Cerebellum",
      "Using a separating funnel"
    ],
    "answer": "Using a separating funnel"
  },
  {
    "question": "The speed of light in a vacuum",
    "options": [
      "The bronchi and lungs",
      "Force × Distance",
      "3 × 10⁸ m/s",
      "A mixture of two or more metals"
    ],
    "answer": "3 × 10⁸ m/s"
  },
  {
    "question": "Decomposers in an ecosystem",
    "options": [
      "A mixture of two or more metals",
      "Current is the same throughout in series",
      "Break down dead organic matter",
      "Gaseous exchange in the lungs"
    ],
    "answer": "Break down dead organic matter"
  },
  {
    "question": "The trachea leads to",
    "options": [
      "The bronchi and lungs",
      "Current is the same throughout in series",
      "Plant growth towards light",
      "Using a separating funnel"
    ],
    "answer": "The bronchi and lungs"
  }
]