[
  {
    "question": "Sylvia Wynter's concept of 'the overrepresentation of Man'",
    "options": [
      "Western humanism's definition of the human excludes Black and colonised peoples",
      "Living in the aftermath of slavery — the ongoing structures of anti-Blackness",
      "Mapping Caribbean space through literature reclaims it from colonial geography",
      "The fugitive, creative space outside official institutions where resistance thrives"
    ],
    "correctIndex": 0
  },
  {
    "question": "The concept of 'poethics' in Caribbean writing",
    "options": [
      "It offers the world a model of creative survival, hybridity and resistance against all forms of oppression",
      "The fugitive, creative space outside official institutions where resistance thrives",
      "Fiction that returns to the plantation to excavate its ongoing legacy",
      "The inseparability of aesthetics and ethics in postcolonial literary practice"
    ],
    "correctIndex": 3
  },
  {
    "question": "The concept of 'the undercommons' (Harney and Moten) applied to Caribbean writing",
    "options": [
      "The fugitive, creative space outside official institutions where resistance thrives",
      "Ideas that escape and exceed the boundaries of Western academic frameworks",
      "Literature can resist full interpretation — meaning need not be transparent",
      "It offers the world a model of creative survival, hybridity and resistance against all forms of oppression"
    ],
    "correctIndex": 0
  },
  {
    "question": "The concept of 'afro-pessimism' vs Caribbean optimism in literature",
    "options": [
      "Afro-pessimism sees anti-Blackness as structural; Caribbean writing often insists on creative survival",
      "Ideas that escape and exceed the boundaries of Western academic frameworks",
      "Imagining alternative histories that restore agency to enslaved and colonised peoples",
      "Western humanism's definition of the human excludes Black and colonised peoples"
    ],
    "correctIndex": 0
  },
  {
    "question": "The concept of 'new world baroque' (Lezama Lima)",
    "options": [
      "An extravagant, syncretic American aesthetic born from the collision of cultures",
      "It offers the world a model of creative survival, hybridity and resistance against all forms of oppression",
      "Creolisation offers a model for all cultures in a globalised, interconnected world",
      "Imagining alternative histories that restore agency to enslaved and colonised peoples"
    ],
    "correctIndex": 0
  },
  {
    "question": "Glissant's concept of 'the right to opacity' in literary terms",
    "options": [
      "History, culture and identity in the Caribbean are inextricably tangled together",
      "An extravagant, syncretic American aesthetic born from the collision of cultures",
      "Literature can resist full interpretation — meaning need not be transparent",
      "It offers the world a model of creative survival, hybridity and resistance against all forms of oppression"
    ],
    "correctIndex": 2
  },
  {
    "question": "The concept of 'fugitive thought' in Caribbean critical theory",
    "options": [
      "The fugitive, creative space outside official institutions where resistance thrives",
      "Living in the aftermath of slavery — the ongoing structures of anti-Blackness",
      "Ideas that escape and exceed the boundaries of Western academic frameworks",
      "Western humanism's definition of the human excludes Black and colonised peoples"
    ],
    "correctIndex": 2
  },
  {
    "question": "The concept of 'entanglement' in Caribbean writing",
    "options": [
      "The fugitive, creative space outside official institutions where resistance thrives",
      "Imagining alternative histories that restore agency to enslaved and colonised peoples",
      "History, culture and identity in the Caribbean are inextricably tangled together",
      "An extravagant, syncretic American aesthetic born from the collision of cultures"
    ],
    "correctIndex": 2
  },
  {
    "question": "The concept of 'the wake' (Sharpe) applied to Caribbean writing",
    "options": [
      "It offers the world a model of creative survival, hybridity and resistance against all forms of oppression",
      "Ideas that escape and exceed the boundaries of Western academic frameworks",
      "Living in the aftermath of slavery — the ongoing structures of anti-Blackness",
      "An extravagant, syncretic American aesthetic born from the collision of cultures"
    ],
    "correctIndex": 2
  },
  {
    "question": "The concept of 'creolisation as world philosophy' (Glissant)",
    "options": [
      "The fugitive, creative space outside official institutions where resistance thrives",
      "Creolisation offers a model for all cultures in a globalised, interconnected world",
      "Western humanism's definition of the human excludes Black and colonised peoples",
      "The inseparability of aesthetics and ethics in postcolonial literary practice"
    ],
    "correctIndex": 1
  },
  {
    "question": "The concept of 'counterfactual fiction' in Caribbean writing",
    "options": [
      "Living in the aftermath of slavery — the ongoing structures of anti-Blackness",
      "Imagining alternative histories that restore agency to enslaved and colonised peoples",
      "Ideas that escape and exceed the boundaries of Western academic frameworks",
      "Literature can resist full interpretation — meaning need not be transparent"
    ],
    "correctIndex": 1
  },
  {
    "question": "The concept of 'the catastrophe' in Caribbean writing",
    "options": [
      "Fiction that returns to the plantation to excavate its ongoing legacy",
      "The rupture of slavery and colonialism as the founding event of Caribbean culture",
      "The inseparability of aesthetics and ethics in postcolonial literary practice",
      "Afro-pessimism sees anti-Blackness as structural; Caribbean writing often insists on creative survival"
    ],
    "correctIndex": 1
  },
  {
    "question": "The concept of 'literary cartography' in Caribbean writing",
    "options": [
      "Creolisation offers a model for all cultures in a globalised, interconnected world",
      "Mapping Caribbean space through literature reclaims it from colonial geography",
      "An extravagant, syncretic American aesthetic born from the collision of cultures",
      "Afro-pessimism sees anti-Blackness as structural; Caribbean writing often insists on creative survival"
    ],
    "correctIndex": 1
  },
  {
    "question": "The concept of 'the plantation novel' as a subgenre",
    "options": [
      "Western humanism's definition of the human excludes Black and colonised peoples",
      "Fiction that returns to the plantation to excavate its ongoing legacy",
      "Literature can resist full interpretation — meaning need not be transparent",
      "It offers the world a model of creative survival, hybridity and resistance against all forms of oppression"
    ],
    "correctIndex": 1
  },
  {
    "question": "The ultimate significance of Caribbean literature globally",
    "options": [
      "Fiction that returns to the plantation to excavate its ongoing legacy",
      "History, culture and identity in the Caribbean are inextricably tangled together",
      "It offers the world a model of creative survival, hybridity and resistance against all forms of oppression",
      "Ideas that escape and exceed the boundaries of Western academic frameworks"
    ],
    "correctIndex": 2
  }
]