[
  {
    "question": "The NDP won the November 2025 election with how many seats",
    "options": [
      "SVG national government",
      "Roasted breadfruit and fried jackfish",
      "Brighton to Black Point on the leeward coast — built in 1815",
      "10 seats to the ULP's 5"
    ],
    "answer": "10 seats to the ULP's 5"
  },
  {
    "question": "The ULP opposition leader after the 2025 election is",
    "options": [
      "Ralph Gonsalves",
      "Arnos Vale Sports Complex",
      "1973",
      "10 seats to the ULP's 5"
    ],
    "answer": "Ralph Gonsalves"
  },
  {
    "question": "SVG's House of Assembly has how many elected members",
    "options": [
      "Three diamonds representing the Gems of the Antilles",
      "15",
      "1765 — one of the oldest in the Western Hemisphere",
      "Arnos Vale Sports Complex"
    ],
    "answer": "15"
  },
  {
    "question": "The Vincentian cricketer who scored a Test century for West Indies is",
    "options": [
      "SVG national government",
      "Lindon James among recent players from SVG",
      "The Movement for National Unity (MNU) and the St. Vincent Labour Party (SVLP)",
      "Ralph Gonsalves"
    ],
    "answer": "Lindon James among recent players from SVG"
  },
  {
    "question": "The Arnos Vale stadium's official name",
    "options": [
      "Arnos Vale Sports Complex",
      "1973",
      "Brighton to Black Point on the leeward coast — built in 1815",
      "Thing — used as a general placeholder noun"
    ],
    "answer": "Arnos Vale Sports Complex"
  },
  {
    "question": "The Black Point Tunnel in SVG connects",
    "options": [
      "Bay Street",
      "Brighton to Black Point on the leeward coast — built in 1815",
      "1765 — one of the oldest in the Western Hemisphere",
      "Ralph Gonsalves"
    ],
    "answer": "Brighton to Black Point on the leeward coast — built in 1815"
  },
  {
    "question": "SVG's main street in Kingstown is",
    "options": [
      "15",
      "Three diamonds representing the Gems of the Antilles",
      "Bay Street",
      "10 seats to the ULP's 5"
    ],
    "answer": "Bay Street"
  },
  {
    "question": "The Vincentian folk song 'Shake Shake Lady' is associated with",
    "options": [
      "Thing — used as a general placeholder noun",
      "SVG national government",
      "Nine Mornings festival tradition",
      "Brighton to Black Point on the leeward coast — built in 1815"
    ],
    "answer": "Nine Mornings festival tradition"
  },
  {
    "question": "The Grenadine island of Canouan is administered under",
    "options": [
      "Ralph Gonsalves",
      "SVG national government",
      "1765 — one of the oldest in the Western Hemisphere",
      "Bay Street"
    ],
    "answer": "SVG national government"
  },
  {
    "question": "SVG's flag diamond shape contains",
    "options": [
      "10 seats to the ULP's 5",
      "Lindon James among recent players from SVG",
      "Three diamonds representing the Gems of the Antilles",
      "Ralph Gonsalves"
    ],
    "answer": "Three diamonds representing the Gems of the Antilles"
  },
  {
    "question": "SVG joined CARICOM at its founding in",
    "options": [
      "SVG national government",
      "Arnos Vale Sports Complex",
      "Ralph Gonsalves",
      "1973"
    ],
    "answer": "1973"
  },
  {
    "question": "The Vincentian patois word 'ting' most commonly means",
    "options": [
      "Three diamonds representing the Gems of the Antilles",
      "Brighton to Black Point on the leeward coast — built in 1815",
      "Bay Street",
      "Thing — used as a general placeholder noun"
    ],
    "answer": "Thing — used as a general placeholder noun"
  },
  {
    "question": "The Botanic Gardens in Kingstown was established in",
    "options": [
      "10 seats to the ULP's 5",
      "1765 — one of the oldest in the Western Hemisphere",
      "1973",
      "Lindon James among recent players from SVG"
    ],
    "answer": "1765 — one of the oldest in the Western Hemisphere"
  },
  {
    "question": "SVG's national dish was officially designated as",
    "options": [
      "Nine Mornings festival tradition",
      "SVG national government",
      "Roasted breadfruit and fried jackfish",
      "The Movement for National Unity (MNU) and the St. Vincent Labour Party (SVLP)"
    ],
    "answer": "Roasted breadfruit and fried jackfish"
  },
  {
    "question": "The former PM Ralph Gonsalves' political party the ULP was formed by a merger of",
    "options": [
      "The Movement for National Unity (MNU) and the St. Vincent Labour Party (SVLP)",
      "Three diamonds representing the Gems of the Antilles",
      "Bay Street",
      "10 seats to the ULP's 5"
    ],
    "answer": "The Movement for National Unity (MNU) and the St. Vincent Labour Party (SVLP)"
  }
]