[
  {
    "question": "Capital city of Vietnam",
    "options": [
      "Hanoi",
      "East Africa",
      "Havana",
      "Budapest"
    ],
    "answer": "Hanoi"
  },
  {
    "question": "The Strait of Dover separates",
    "options": [
      "Havana",
      "Athens",
      "England and France",
      "Santiago"
    ],
    "answer": "England and France"
  },
  {
    "question": "Capital city of Portugal",
    "options": [
      "Budapest",
      "Lisbon",
      "Havana",
      "The North Sea"
    ],
    "answer": "Lisbon"
  },
  {
    "question": "The world's largest lake by surface area",
    "options": [
      "Caspian Sea",
      "England and France",
      "Hanoi",
      "Lisbon"
    ],
    "answer": "Caspian Sea"
  },
  {
    "question": "Capital city of Chile",
    "options": [
      "Sucre (constitutional) / La Paz (seat of government)",
      "Santiago",
      "Havana",
      "East Africa"
    ],
    "answer": "Santiago"
  },
  {
    "question": "The Amazon Basin covers approximately",
    "options": [
      "The North Sea",
      "Caspian Sea",
      "Lisbon",
      "40% of South America"
    ],
    "answer": "40% of South America"
  },
  {
    "question": "Capital city of Greece",
    "options": [
      "Sucre (constitutional) / La Paz (seat of government)",
      "Lisbon",
      "Abu Dhabi",
      "Athens"
    ],
    "answer": "Athens"
  },
  {
    "question": "The continent with the fewest countries",
    "options": [
      "Hanoi",
      "The Great Barrier Reef, Australia",
      "Australia/Oceania",
      "Caspian Sea"
    ],
    "answer": "Australia/Oceania"
  },
  {
    "question": "Capital city of Cuba",
    "options": [
      "40% of South America",
      "Havana",
      "East Africa",
      "The North Sea"
    ],
    "answer": "Havana"
  },
  {
    "question": "The Rhine River flows into",
    "options": [
      "The North Sea",
      "Caspian Sea",
      "40% of South America",
      "Lisbon"
    ],
    "answer": "The North Sea"
  },
  {
    "question": "Capital city of the United Arab Emirates",
    "options": [
      "The Great Barrier Reef, Australia",
      "East Africa",
      "Caspian Sea",
      "Abu Dhabi"
    ],
    "answer": "Abu Dhabi"
  },
  {
    "question": "The island of Madagascar lies off the coast of",
    "options": [
      "East Africa",
      "Australia/Oceania",
      "Sucre (constitutional) / La Paz (seat of government)",
      "Budapest"
    ],
    "answer": "East Africa"
  },
  {
    "question": "Capital city of Bolivia",
    "options": [
      "Abu Dhabi",
      "Sucre (constitutional) / La Paz (seat of government)",
      "Havana",
      "The North Sea"
    ],
    "answer": "Sucre (constitutional) / La Paz (seat of government)"
  },
  {
    "question": "The world's longest reef system is",
    "options": [
      "The Great Barrier Reef, Australia",
      "Havana",
      "The North Sea",
      "Abu Dhabi"
    ],
    "answer": "The Great Barrier Reef, Australia"
  },
  {
    "question": "Capital city of Hungary",
    "options": [
      "Abu Dhabi",
      "40% of South America",
      "Athens",
      "Budapest"
    ],
    "answer": "Budapest"
  }
]